meeshkan_hosted_secrets/__init__.py
meeshkan_hosted_secrets-0.6.dist-info/LICENSE
meeshkan_hosted_secrets-0.6.dist-info/METADATA
meeshkan_hosted_secrets-0.6.dist-info/WHEEL
meeshkan_hosted_secrets-0.6.dist-info/top_level.txt
meeshkan_hosted_secrets-0.6.dist-info/RECORD
