Metadata-Version: 2.1
Name: meeshkan-hosted-secrets
Version: 0.6
Summary: Utility package to access Secret Manager on meeshkan.io
Home-page: https://github.com/meeshkan/meeshkan-hosted-secrets
Author: Meeshkan Dev Team
Author-email: dev@meeshkan.com
License: MIT
Platform: UNKNOWN
Requires-Dist: google-cloud-secret-manager (==1.0.0)
